pykoala/__init__.py
pykoala/_version.py
pykoala/ancillary.py
pykoala/cubing.py
pykoala/data_container.py
pykoala/photometry.py
pykoala/rss.py
pykoala/corrections/__init__.py
pykoala/corrections/astrometry.py
pykoala/corrections/atmospheric_corrections.py
pykoala/corrections/correction.py
pykoala/corrections/flux_calibration.py
pykoala/corrections/sky.py
pykoala/corrections/throughput.py
pykoala/corrections/wavelength.py
pykoala/exceptions/__init__.py
pykoala/exceptions/exceptions.py
pykoala/input_data/emission_line_list.dat
pykoala/input_data/observatory_extinction/ssoextinct.dat
pykoala/input_data/sky_lines/sky_lines.dat
pykoala/input_data/sky_lines/sky_lines_IR.dat
pykoala/input_data/sky_lines/sky_lines_IR_short.dat
pykoala/input_data/sky_lines/sky_lines_bright.dat
pykoala/input_data/sky_lines/sky_lines_rest.dat
pykoala/input_data/sky_lines/skylines_2dFdr.txt
pykoala/input_data/sky_lines/telluric_lines.txt
pykoala/input_data/sky_lines/ESO-UVES/gident_346.tfits
pykoala/input_data/sky_lines/ESO-UVES/gident_437.tfits
pykoala/input_data/sky_lines/ESO-UVES/gident_580L.tfits
pykoala/input_data/sky_lines/ESO-UVES/gident_580U.tfits
pykoala/input_data/sky_lines/ESO-UVES/gident_800U.tfits
pykoala/input_data/sky_lines/ESO-UVES/gident_860L.tfits
pykoala/input_data/sky_lines/ESO-UVES/gident_860U.tfits
pykoala/input_data/spectrophotometric_stars/fcd32d9927.dat
pykoala/input_data/spectrophotometric_stars/feg21.dat
pykoala/input_data/spectrophotometric_stars/feg21_edited.dat
pykoala/input_data/spectrophotometric_stars/feg274.dat
pykoala/input_data/spectrophotometric_stars/feg274_edited.dat
pykoala/input_data/spectrophotometric_stars/ffeige110.dat
pykoala/input_data/spectrophotometric_stars/ffeige110_edited.dat
pykoala/input_data/spectrophotometric_stars/ffeige56.dat
pykoala/input_data/spectrophotometric_stars/ffeige56_edited.dat
pykoala/input_data/spectrophotometric_stars/fhd49798.dat
pykoala/input_data/spectrophotometric_stars/fhd60753.dat
pykoala_ifs-0.18.3.dist-info/licenses/LICENSE
pykoala_ifs-0.18.3.dist-info/METADATA
pykoala_ifs-0.18.3.dist-info/WHEEL
pykoala_ifs-0.18.3.dist-info/top_level.txt
pykoala_ifs-0.18.3.dist-info/RECORD
