Metadata-Version: 2.4
Name: pykoala-ifs
Version: 0.18.3
Summary: Data reduction tools for IFS data.
Author-email: Pablo Corcho-Caballero <p.corcho.caballero@rug.nl>, "Ángel R. López-Sánchez" <angel.lopez-sanchez@mq.edu.au>, Yago Ascasibar <yago.ascasibar@uam.es>
License: BSD-3-Clause
Project-URL: Homepage, https://github.com/pykoala/koala
Project-URL: Issues, https://github.com/pykoala/koala/issues
Keywords: astronomy,IFS,data reduction
Classifier: Development Status :: 4 - Beta
Classifier: Intended Audience :: Science/Research
Classifier: License :: OSI Approved :: BSD License
Classifier: Topic :: Scientific/Engineering
Classifier: Programming Language :: Python :: 3
Classifier: Operating System :: OS Independent
Requires-Python: >=3.9
License-File: LICENSE
Dynamic: license-file
